comike_cli/__init__.py
comike_cli/agent.py
comike_cli/api.py
comike_cli/auth.py
comike_cli/config.py
comike_cli/database.py
comike_cli/image.py
comike_cli/main.py
comike_cli-0.107.1.dist-info/METADATA
comike_cli-0.107.1.dist-info/WHEEL
comike_cli-0.107.1.dist-info/entry_points.txt
comike_cli-0.107.1.dist-info/licenses/LICENSE
comike_cli-0.107.1.dist-info/RECORD
