Metadata-Version: 2.4
Name: comike-cli
Version: 0.107.1
Summary: CLI tool for Comiket WebCatalog with natural language interface
Project-URL: Homepage, https://github.com/m96-chan/comike-cli
Project-URL: Repository, https://github.com/m96-chan/comike-cli
Project-URL: Issues, https://github.com/m96-chan/comike-cli/issues
Author: m96-chan
License-Expression: MIT
License-File: LICENSE
Keywords: catalog,circle.ms,cli,comiket,doujin
Classifier: Development Status :: 3 - Alpha
Classifier: Environment :: Console
Classifier: Intended Audience :: End Users/Desktop
Classifier: License :: OSI Approved :: MIT License
Classifier: Operating System :: OS Independent
Classifier: Programming Language :: Python :: 3
Classifier: Programming Language :: Python :: 3.10
Classifier: Programming Language :: Python :: 3.11
Classifier: Programming Language :: Python :: 3.12
Classifier: Programming Language :: Python :: 3.13
Classifier: Topic :: Utilities
Requires-Python: >=3.10
Requires-Dist: httpx>=0.25.0
Requires-Dist: openai>=1.0.0
Requires-Dist: pillow>=10.0.0
Requires-Dist: prompt-toolkit>=3.0.0
Requires-Dist: python-dotenv>=1.0.0
Requires-Dist: rich>=13.0.0
Provides-Extra: dev
Requires-Dist: pytest>=7.0.0; extra == 'dev'
Requires-Dist: ruff>=0.1.0; extra == 'dev'
